LICENSE
MANIFEST.in
README.rst
setup.cfg
setup.py
bitfield/__init__.py
bitfield/admin.py
bitfield/apps.py
bitfield/compat.py
bitfield/forms.py
bitfield/models.py
bitfield/query.py
bitfield/types.py
bitfield/tests/__init__.py
bitfield/tests/forms.py
bitfield/tests/models.py
bitfield/tests/tests.py
django_gravy_bitfield.egg-info/PKG-INFO
django_gravy_bitfield.egg-info/SOURCES.txt
django_gravy_bitfield.egg-info/dependency_links.txt
django_gravy_bitfield.egg-info/not-zip-safe
django_gravy_bitfield.egg-info/requires.txt
django_gravy_bitfield.egg-info/top_level.txt