Metadata-Version: 1.1
Name: django-gravy-bitfield
Version: 1.9.1
Summary: BitField in Django
Home-page: https://github.com/disqus/django-bitfield
Author: DISQUS
Author-email: opensource@disqus.com
License: Apache License
Platform: UNKNOWN
Classifier: Framework :: Django
Classifier: Intended Audience :: Developers
Classifier: Intended Audience :: System Administrators
Classifier: Operating System :: OS Independent
Classifier: Topic :: Software Development
Classifier: Programming Language :: Python
Classifier: Programming Language :: Python :: 2
Classifier: Programming Language :: Python :: 2.7
Classifier: Programming Language :: Python :: 3
Classifier: Programming Language :: Python :: 3.4
Classifier: Programming Language :: Python :: 3.5
